persistent_cache/__init__.py
persistent_cache/py.typed
persistent_cache/caches/__init__.py
persistent_cache/caches/deep_learning.py
persistent_cache/caches/speedup_deep_learning.py
persistent_cache/cli/__init__.py
persistent_cache/cli/clear_cache.py
persistent_cache/main/__init__.py
persistent_cache/main/cache_slot.py
persistent_cache/main/decorator.py
persistent_cache/main/hashing.py
persistent_cache/models/__init__.py
persistent_cache/models/path.py
persistent_cache/reducers/__init__.py
persistent_cache/reducers/base.py
persistent_cache/reducers/deep_learning.py
persistent_cache/reducers/speedup_deep_learning.py
persistent_function_cache-0.2.2.dist-info/LICENSE
persistent_function_cache-0.2.2.dist-info/METADATA
persistent_function_cache-0.2.2.dist-info/WHEEL
persistent_function_cache-0.2.2.dist-info/entry_points.txt
persistent_function_cache-0.2.2.dist-info/top_level.txt
persistent_function_cache-0.2.2.dist-info/RECORD
