Metadata-Version: 2.2
Name: persistent-function-cache
Version: 0.2.2
Summary: Persistent cache for expensive functions
Author-email: Quinten Roets <qdr2104@columbia.edu>
License: MIT
Project-URL: Source Code, https://github.com/quintenroets/persistent-cache
Requires-Python: <3.13,>=3.10
License-File: LICENSE
Requires-Dist: package-utils<1,>=0.6.7
Requires-Dist: powercli<1,>=0.3.2
Requires-Dist: superpathlib<3,>=2.0.9
Provides-Extra: dev
Requires-Dist: package-dev-tools<1,>=0.5.11; extra == "dev"
Requires-Dist: package-dev-utils<1,>=0.1.6; extra == "dev"
Requires-Dist: numpy<3,>=1.26.0; extra == "dev"
Requires-Dist: torch<3,>=1.26.0; extra == "dev"
